winaccent/__init__.py
winaccent/__main__.py
winaccent/_utils.py
winaccent/_win_10.py
winaccent/_win_8.py
winaccent-2.1.0.dist-info/LICENSE
winaccent-2.1.0.dist-info/METADATA
winaccent-2.1.0.dist-info/WHEEL
winaccent-2.1.0.dist-info/top_level.txt
winaccent-2.1.0.dist-info/RECORD
