Metadata-Version: 2.1
Name: winaccent
Version: 2.1.0
Summary: A simple and lightweight Python module for easily retrieving Windows' accent color, including shades, specific window chrome colors such as active/inactive titlebar and window borders and theme. Supports Windows 8.x, 10 and 11 and doesn't require additional dependencies.
Home-page: https://github.com/Valer100/winaccent
Author: Valer100
Maintainer: Valer100
License: MIT
Project-URL: Source, https://github.com/Valer100/winaccent
Project-URL: Documentation, https://valer100.github.io/winaccent
Project-URL: Changelog, https://valer100.github.io/winaccent/about/changelog
Project-URL: Issues, https://github.com/Valer100/winaccent/issues
Keywords: accent,accent-light,accent-dark,accent-coloraccent-palette,dark-mode,light-mode,system-theme,color,theme,modern,gui,win32,fluent,sun-valley,windows-11,windows-10,windows-8,winui,winaccent
Classifier: Intended Audience :: Developers
Classifier: Programming Language :: Python :: 3 :: Only
Classifier: Programming Language :: Python :: 3.6
Classifier: Programming Language :: Python :: 3.7
Classifier: Programming Language :: Python :: 3.8
Classifier: Programming Language :: Python :: 3.9
Classifier: Programming Language :: Python :: 3.10
Classifier: Programming Language :: Python :: 3.11
Classifier: Programming Language :: Python :: 3.12
Classifier: Programming Language :: Python :: 3.13
Classifier: License :: OSI Approved :: MIT License
Classifier: Operating System :: Microsoft :: Windows
Classifier: Operating System :: Microsoft :: Windows :: Windows 8
Classifier: Operating System :: Microsoft :: Windows :: Windows 8.1
Classifier: Operating System :: Microsoft :: Windows :: Windows 10
Classifier: Operating System :: Microsoft :: Windows :: Windows 11
Requires-Python: >=3.6
License-File: LICENSE
